crypgm/__init__.py
crypgm-0.0.1.dist-info/METADATA
crypgm-0.0.1.dist-info/WHEEL
crypgm-0.0.1.dist-info/top_level.txt
crypgm-0.0.1.dist-info/RECORD
